<?xml version="1.0" encoding="utf-8" ?>
<Suite Title="ContextualWeb" Identifier="ContextualWeb" RequireVersion="8.2" Category="SEO" SourceUrl="https://github.com/nielsbosma/SeoTools-for-Excel-Connectors/blob/master/ContextualWeb.xml" HelpUrl="http://seotoolsforexcel.com/contextualweb/" HelpText="Documentation">

  <Author Name="Victor" Url="http://community.seotoolsforexcel.com/users/diskborste/activity"/>

  <RestConnector Title="Web" Id="Web" HelpUrl="https://contextualwebsearch.com/freeapi">
    <Parameters>
      <Text Id="Query" Title="Query" Required="true" Debug.DefaultValue=""/>
      <Checkbox Id="Autocorrect" Title="Autocorrect spelling" DefaultValue="False"/>
    </Parameters>
    <Paging PageSize="50" EvenPages="true"/>
    <Fetch>
      <Fetch.Url>
        <![CDATA[
          https://contextualwebsearch.com/api/Search/WebSearchAPIWithPagination
					?q=@Utils.UrlEncode(Model.Query)
					&pageNumber=@(Model.PageCursor.Page+1)
					&pageSize=@Model.PageCursor.NextTake
					&autoCorrect=@Model.Autocorrect
        ]]>
      </Fetch.Url>
    </Fetch>
    <Parse>
      <JsonPath Expr="value.*">
        <JsonPath Expr="url" Id="Url" Title="URL" Converter="String" DefaultValue=""/>
        <Compute Expr="@Utils.StripTags(Model.Inp)" Id="Title" Title="Title">
				<JsonPath Expr="title" Id="Inp" Converter="String" DefaultValue=""/>
        </Compute>
        <Compute Expr="@Utils.StripTags(Model.Inp)" Id="Description" Title="Description">
				<JsonPath Expr="description" Id="Inp" Converter="String"/>
        </Compute>
        <JsonPath Expr="datePublished" Id="Published" Title="Published" Converter="Auto" DefaultValue=""/>
        <JsonPath Expr="provider.name" Id="Provider" Title="Provider" Converter="String" DefaultValue=""/>
        <JsonPath Expr="language" Id="Language" Title="Language" Converter="String" DefaultValue=""/>
        <JsonPath Expr="isSafe" Id="Safe" Title="Safe" Converter="Bool" DefaultValue=""/>
      </JsonPath>
      <JsonPath Expr="totalCount" Id="TotalCount" Converter="Long" DefaultValue="" Checked="false"/>
    </Parse>
  </RestConnector>

  <RestConnector Title="News" Id="News" HelpUrl="https://contextualwebsearch.com/freeapi">
    <Parameters>
      <Text Id="Query" Title="Query" Required="true" Debug.DefaultValue=""/>
      <Checkbox Id="Autocorrect" Title="Autocorrect spelling" DefaultValue="False"/>
    </Parameters>
    <Paging PageSize="50" EvenPages="true"/>
    <Fetch>
      <Fetch.Url>
        <![CDATA[
          https://contextualwebsearch.com/api/Search/NewsSearchAPIWithPagination
					?q=@Utils.UrlEncode(Model.Query)
					&pageNumber=@(Model.PageCursor.Page+1)
					&pageSize=@Model.PageCursor.NextTake
					&autoCorrect=@Model.Autocorrect
        ]]>
      </Fetch.Url>
    </Fetch>
    <Parse>
      <JsonPath Expr="value.*">
        <JsonPath Expr="url" Id="Url" Title="URL" Converter="String" DefaultValue=""/>
        <Compute Expr="@Utils.StripTags(Model.Inp)" Id="Title" Title="Title">
				<JsonPath Expr="title" Id="Inp" Converter="String"/>
        </Compute>
        <Compute Expr="@Utils.StripTags(Model.Inp)" Id="Description" Title="Description">
				<JsonPath Expr="description" Id="Inp" Converter="String" DefaultValue=""/>
        </Compute>
        <JsonPath Expr="datePublished" Id="Published" Title="Published" Converter="Auto" DefaultValue=""/>
        <JsonPath Expr="provider.name" Id="Provider" Title="Provider" Converter="String" DefaultValue=""/>
        <JsonPath Expr="language" Id="Language" Title="Language" Converter="String" DefaultValue=""/>
        <JsonPath Expr="isSafe" Id="Safe" Title="Safe" Converter="Bool" DefaultValue=""/>
      </JsonPath>
      <JsonPath Expr="totalCount" Id="TotalCount" Converter="Long" DefaultValue="" Checked="false"/>
    </Parse>
  </RestConnector>

  <RestConnector Title="Images" Id="Images" HelpUrl="https://contextualwebsearch.com/freeapi">
    <Parameters>
      <Text Id="Query" Title="Query" Required="true" Debug.DefaultValue=""/>
      <Checkbox Id="Autocorrect" Title="Autocorrect spelling" DefaultValue="False"/>
      <Number Id="Count" Title="Count" DefaultValue="50" Minimum="1" Maximum="50" Required="false" HelpText=""/>
    </Parameters>
    <Fetch>
      <Fetch.Url>
        <![CDATA[
          https://contextualwebsearch.com/api/Search/ImageSearchAPI
					?q=@Utils.UrlEncode(Model.Query)
					&count=@Model.Count
					&autoCorrect=@Model.Autocorrect
        ]]>
      </Fetch.Url>
    </Fetch>
    <Parse>
      <JsonPath Expr="value.*">
        <JsonPath Expr="url" Id="Url" Title="URL" Converter="String" DefaultValue=""/>
        <JsonPath Expr="height" Id="Height" Title="Height" Converter="Long" DefaultValue=""/>
        <JsonPath Expr="width" Id="Width" Title="Width" Converter="Long" DefaultValue=""/>
        <JsonPath Expr="thumbnail" Id="Thumbnail" Title="Thumbnail" Converter="String" DefaultValue=""/>
        <JsonPath Expr="thumbnailHeight" Id="ThumbnailHeight" Title="Thumbnail Height" Converter="Long" DefaultValue=""/>
        <JsonPath Expr="thumbnailWidth" Id="ThumbnailWidth" Title="Thumbnail Width" Converter="Long" DefaultValue=""/>
      </JsonPath>
    </Parse>
  </RestConnector>

</Suite>