<?xml version="1.0" encoding="utf-8" ?>
<Suite Category="Domains" RequireVersion="8.2" Title="Domains" Id="DomainsDbSearch" SourceUrl="https://github.com/nielsbosma/SeoTools-for-Excel-Connectors/blob/master/DomainsDbSearch.xml" HelpUrl="http://seotoolsforexcel.com/domains-db-search/" HelpText="Documentation">

  <Author Name="Victor" Url="http://community.seotoolsforexcel.com/users/diskborste/activity"/>

  <RestConnector Id="DomainsDbSearch" Title="Domains" HelpUrl="https://domainsdb.info/">
    <Parameters>
      <Text Id="Query" Title="Query" Debug.DefaultValue="facebook" Required="true"/>
			<Select Id="Database">
				<DataSource>
					<Item Id="all" Title="All"/>
					<Item Id="cc" Title="ccTLD Domains"/>
					<Item Id="g" Title="gTLD Domains"/>
				</DataSource>
			</Select>
    </Parameters>
    <Fetch>
      <HttpSettings>
        <Cache>True</Cache>
      </HttpSettings>
      <Fetch.Url>
        <![CDATA[
        https://api.domainsdb.info/search?query=@(Model.Query)&tld=@(Model.Database)
        ]]>
      </Fetch.Url>
    </Fetch>
    <Parse>
			<JsonPath Expr="domains.*">
				<JsonPath Expr="domain" Id="Domain" Converter="String" DefaultValue=""/>
				<JsonPath Expr="suffix" Id="Suffix" Converter="String" DefaultValue="" Checked="false"/>
				<JsonPath Expr="country" Id="Country" DefaultValue="" Converter="Auto" Checked="false"/>
				<JsonPath Expr="create_date" Id="Created" Converter="Auto" DefaultValue="" Checked="false"/>
				<JsonPath Expr="update_date" Id="Updated" Converter="Auto" DefaultValue="" Checked="false"/>
				<JsonPath Expr="expire_date" Id="Expires" Converter="Auto" DefaultValue="" Checked="false"/>
				<JsonPath Expr="A[0]" Id="Ip" Converter="String" DefaultValue="" Checked="false"/>
				<JsonPath Expr="TXT[0]" Id="TX" Converter="String" DefaultValue="" Checked="false"/>
				<JsonPath Expr="csv(NS)" Id="NS" Title="Name Server" Converter="Auto" DefaultValue="" Checked="true"/>
				<JsonPath Expr="MX[0].exchange" Id="MX" Title="Mail Exchange Record" Converter="String" DefaultValue="" Checked="false"/>
				<JsonPath Expr="is_dead" Id="Dead" Converter="Bool" DefaultValue="" Checked="false"/>
				<JsonPath Expr="resolvable" Id="Resolvable" Converter="Bool" DefaultValue="" Checked="false"/>
			</JsonPath>
			<JsonPath Expr="total" Id="Total" Converter="Long" DefaultValue=""/>
    </Parse>
    <Fail>
      <JsonPath Expr="error"/>
    </Fail>
  </RestConnector>

</Suite>