<?xml version="1.0" encoding="utf-8" ?>
<Suite Category="Language" Title="Gavagai" Identifier="Gavagai" RequireVersion="8.2" SourceUrl="https://github.com/nielsbosma/SeoTools-for-Excel-Connectors/blob/master/Gavagai.xml" HelpUrl="http://seotoolsforexcel.com/gavagai/" HelpText="Documentation">

  <Author Name="Victor" Url="http://community.seotoolsforexcel.com/users/diskborste/activity"/>

  <Settings HelpText="What's this?" HelpUrl="http://seotoolsforexcel.com/gavagai/">
    <Text Id="Key" Title="API Key" Required="true"/>
  </Settings>

  <Resources>
    <Resource Id="Languages">
      <Select Id="Language" Title="Language" Required="true" DefaultValue="en">
        <DataSource>
					<Item Id="ar" Title="Arabic"/>
					<Item Id="az" Title="Azerbaijani"/>
					<Item Id="bg" Title="Bulgarian"/>
					<Item Id="bn" Title="Bengali"/>
					<Item Id="ca" Title="Catalan, Valencian"/>
					<Item Id="cs" Title="Czech"/>
					<Item Id="da" Title="Danish"/>
					<Item Id="de" Title="German"/>
					<Item Id="el" Title="Greek, Modern (1453-)"/>
					<Item Id="en" Title="English"/>
					<Item Id="es" Title="Spanish, Castilian"/>
					<Item Id="et" Title="Estonian"/>
					<Item Id="fa" Title="Persian"/>
					<Item Id="fi" Title="Finnish"/>
					<Item Id="fr" Title="French"/>
					<Item Id="he" Title="Hebrew"/>
					<Item Id="hi" Title="Hindi"/>
					<Item Id="hr" Title="Croatian"/>
					<Item Id="hu" Title="Hungarian"/>
					<Item Id="id" Title="Indonesian"/>
					<Item Id="is" Title="Icelandic"/>
					<Item Id="it" Title="Italian"/>
					<Item Id="ja" Title="Japanese"/>
					<Item Id="jv" Title="Javanese"/>
					<Item Id="ko" Title="Korean"/>
					<Item Id="lt" Title="Lithuanian"/>
					<Item Id="lv" Title="Latvian"/>
					<Item Id="ms" Title="Malay"/>
					<Item Id="nl" Title="Dutch, Flemish"/>
					<Item Id="no" Title="Norwegian"/>
        </DataSource>
      </Select>
    </Resource>
    <Resource Id="HttpSettings">
			<RequestContentType>application/json</RequestContentType>
			<RequestHeaders>
				<Header Name='Accept'>application/json;charset=UTF-8</Header>
			</RequestHeaders>
    </Resource>
    <Resource Id="Error">
      <Fail>
				<JsonPath Expr="message"/>
      </Fail>
    </Resource>
  </Resources>

  <RestConnector Id="FrequencyRanking" Title="Frequency and Ranking" HelpUrl="https://developer.gavagai.se/docs">
    <Parameters>
      <Text Id="Text" Title="Text" DefaultValue="" Required="true"/>
			<Resource Id="Languages"/>
    </Parameters>
    <Fetch>
			<Resource Id="HttpSettings"/>
      <Fetch.Url>
        <![CDATA[
					https://api.gavagai.se/v3/lexicon/@Model.Language/@Utils.UrlEncode(Model.Text)?apiKey=@Model.Key
					]]>
      </Fetch.Url>
    </Fetch>
    <Parse>
      <JsonPath Expr="$.wordInformation.frequency" Id="Frequency" Title="Frequency" Converter="Int"/>
      <JsonPath Expr="$.wordInformation.documentFrequency" Id="DocumentFrequency" Title="Document Frequency" Converter="Int"/>
    </Parse>
    <Resource Id="Error"/>
  </RestConnector>

  <RestConnector Id="StringSimilar" Title="Similarity from String" Group="Similar Words" HelpUrl="https://developer.gavagai.se/docs">
    <Parameters>
      <Text Id="Text" Title="Text" DefaultValue="" Required="true"/>
			<Resource Id="Languages"/>
    </Parameters>
    <Fetch>
			<Resource Id="HttpSettings"/>
      <Fetch.Url>
        <![CDATA[
					https://api.gavagai.se/v3/lexicon/@Model.Language/@Utils.UrlEncode(Model.Text)?apiKey=@Model.Key
					]]>
      </Fetch.Url>
    </Fetch>
    <Parse>
      <JsonPath Expr="stringSimilarWords[*]">
        <JsonPath Expr="word" Id="StringWord" Title="Similar Words" Converter="String"/>
      </JsonPath>
    </Parse>
    <Resource Id="Error"/>
  </RestConnector>

  <RestConnector Id="SemanticallySimilar" Title="Similarity from Semantics" Group="Similar Words" HelpUrl="https://developer.gavagai.se/docs">
    <Parameters>
      <Text Id="Text" Title="Text" DefaultValue="" Required="true"/>
			<Resource Id="Languages"/>
    </Parameters>
    <Fetch>
			<Resource Id="HttpSettings"/>
      <Fetch.Url>
        <![CDATA[
					https://api.gavagai.se/v3/lexicon/@Model.Language/@Utils.UrlEncode(Model.Text)?apiKey=@Model.Key
					]]>
      </Fetch.Url>
    </Fetch>
    <Parse>
      <JsonPath Expr="semanticallySimilarWordFilaments[*].words[*]">
        <JsonPath Expr="word" Id="SemanticalWord" Title="Semantically Similar Words" Converter="String"/>
        <JsonPath Expr="strength" Id="SemanticalStrength" Title="Strength" Converter="Double"/>
      </JsonPath>
    </Parse>
    <Resource Id="Error"/>
  </RestConnector>

  <RestConnector Id="TopicSimilar" Title="Similarity from Topic" Group="Similar Words" HelpUrl="https://developer.gavagai.se/docs">
    <Parameters>
      <Text Id="Text" Title="Text" DefaultValue="" Required="true"/>
			<Resource Id="Languages"/>
    </Parameters>
    <Fetch>
			<Resource Id="HttpSettings"/>
      <Fetch.Url>
        <![CDATA[
					https://api.gavagai.se/v3/lexicon/@Model.Language/@Utils.UrlEncode(Model.Text)?apiKey=@Model.Key
					]]>
      </Fetch.Url>
    </Fetch>
    <Parse>
      <JsonPath Expr="topicalFilaments[*].words[*]">
        <JsonPath Expr="word" Id="TopicalWord" Title="Topically Similar Words" Converter="String"/>
        <JsonPath Expr="strength" Id="TopicalStrength" Title="Strength" Converter="Double"/>
      </JsonPath>
    </Parse>
    <Resource Id="Error"/>
  </RestConnector>

  <RestConnector Id="BeginsWith" Title="Words Beginning With" Group="Similar Words" HelpUrl="https://developer.gavagai.se/docs">
    <Parameters>
      <Text Id="Text" Title="Text" DefaultValue="" Required="true"/>
			<Resource Id="Languages"/>
    </Parameters>
    <Fetch>
			<Resource Id="HttpSettings"/>
      <Fetch.Url>
        <![CDATA[
					https://api.gavagai.se/v3/lexicon/@Model.Language/@Utils.UrlEncode(Model.Text)?apiKey=@Model.Key
					]]>
      </Fetch.Url>
    </Fetch>
    <Parse>
      <JsonPath Expr="startsWithWords[*]">
        <JsonPath Expr="word" Id="StartsWithWords" Title="Words Beginning With" Converter="String"/>
      </JsonPath>
    </Parse>
    <Resource Id="Error"/>
  </RestConnector>

  <RestConnector Id="EndsWith" Title="Words Ending With" Group="Similar Words" HelpUrl="https://developer.gavagai.se/docs">
    <Parameters>
      <Text Id="Text" Title="Text" DefaultValue="" Required="true"/>
			<Resource Id="Languages"/>
    </Parameters>
    <Fetch>
			<Resource Id="HttpSettings"/>
      <Fetch.Url>
        <![CDATA[
					https://api.gavagai.se/v3/lexicon/@Model.Language/@Utils.UrlEncode(Model.Text)?apiKey=@Model.Key
					]]>
      </Fetch.Url>
    </Fetch>    <Parse>
      <JsonPath Expr="endsWithWords[*]">
        <JsonPath Expr="word" Id="WndsWithWords" Title="Words Ending With" Converter="String"/>
      </JsonPath>
    </Parse>
    <Resource Id="Error"/>
  </RestConnector>

  <RestConnector Id="Tonality" Title="Tonality" HelpUrl="https://developer.gavagai.se/docs">
    <Parameters>
      <Text Id="Text" Title="Text" Debug.DefaultValue="I'm so happy" Required="true"/>
			<Resource Id="Languages"/>
    </Parameters>
    <Fetch Url="https://api.gavagai.se/v3/tonality/?apiKey=@Model.Key">
      <HttpSettings>
        <RequestMethod>POST</RequestMethod>
				<RequestHeaders>
					<Header Name='Accept'>application/json;charset=UTF-8</Header>
				</RequestHeaders>
        <RequestContentType>application/json</RequestContentType>
        <RequestBody>
					{
						"texts": [
							{
								"body": "@Model.Text",
								"title": "placeholder",
								"id": "placeholder"
							}
						],
						"language": "@Model.Language"
					}
        </RequestBody>
      </HttpSettings>
    </Fetch>
    <Parse>
      <JsonPath Expr="texts.*">
        <JsonPath Expr="tonality[?(@@.tone=='love')].score" Id="Love" Title="Love" Converter="Double" />
        <JsonPath Expr="tonality[?(@@.tone=='positivity')].score" Id="Positivity" Title="Positivity" Converter="Double" />
        <JsonPath Expr="tonality[?(@@.tone=='desire')].score" Id="Desire" Title="Desire" Converter="Double" />
        <JsonPath Expr="tonality[?(@@.tone=='skepticism')].score" Id="Skepticism" Title="Skepticism" Converter="Double" />
        <JsonPath Expr="tonality[?(@@.tone=='negativity')].score" Id="Negativity" Title="Negativity" Converter="Double" />
        <JsonPath Expr="tonality[?(@@.tone=='fear')].score" Id="Fear" Title="Fear" Converter="Double" />
        <JsonPath Expr="tonality[?(@@.tone=='hate')].score" Id="Hate" Title="Hate" Converter="Double" />
        <JsonPath Expr="tonality[?(@@.tone=='violence')].score" Id="Violence" Title="Violence" Converter="Double" />
      </JsonPath>
    </Parse>
    <Resource Id="Error"/>
  </RestConnector>

</Suite>