<?xml version="1.0" encoding="utf-8" ?>
<Suite Category="SEO" RequireVersion="8.1.0" Title="Serpstat" Id="Serpstat" SourceUrl="https://github.com/nielsbosma/SeoTools-for-Excel-Connectors/blob/master/Serpstat.xml" HelpUrl="http://seotoolsforexcel.com/Serpstat/" HelpText="Documentation">

  <Author Name="Victor" Url="http://community.seotoolsforexcel.com/users/diskborste/activity"/>

  <Settings HelpText="What's this?" HelpUrl="http://seotoolsforexcel.com/Serpstat/">
    <Text Id="Key" Title="API Key" Required="true"/>
  </Settings>

  <Resources>
    <Resource Id="SelectEngine">
      <Select Id="Engine" Title="Engine" Required="true" DefaultValue="g_us">
        <DataSource>
          <Item Id="g_us" Title="Google USA"/>
          <Item Id="g_uk" Title="Google Great Britain"/>
          <Item Id="g_au" Title="Google Australia"/>
          <Item Id="g_ru" Title="Google Russia"/>
          <Item Id="g_ca" Title="Google Canada"/>
          <Item Id="g_bg" Title="Google Bulgaria"/>
          <Item Id="g_ua" Title="Google Ukraine"/>
          <Item Id="g_za" Title="Google South Africa"/>
          <Item Id="g_lt" Title="Google Lithuania"/>
          <Item Id="g_lv" Title="Google Latvia"/>
          <Item Id="g_by" Title="Google Belarus"/>
          <Item Id="g_kz" Title="Google Kazakhstan"/>
          <Item Id="y_213" Title="Yandex Moscow"/>
          <Item Id="y_2" Title="Yandex Saint Petersburg"/>
          <Item Id="y_187" Title="Yandex Ukraine"/>
        </DataSource>
      </Select>
    </Resource>
  </Resources>

  <RestConnector Id="DomainSummary" Title="Domain Summary" Group="Domain Reports" HelpText="This report provides you with the number of keywords domain uses in SEO and PPC, shows its online visibility and other metrics." HelpUrl="https://serpstat.com/api/14-domain-summary-report-domaininfo/">
    <Parameters>
      <Text Id="Domain" Title="Domain" Debug.DefaultValue="apple.com" Required="true"/>
      <Resource Id="SelectEngine"/>
    </Parameters>
    <Fetch>
      <Fetch.Url>
        <![CDATA[
        http://api.serpstat.com/v3/domain_info?token=@Model.Key
        &query=@Utils.UrlEncode(Model.Domain)
        &se=@Model.Engine
        ]]>
      </Fetch.Url>
    </Fetch>
    <Parse>
      <JsonPath Expr="result.domain" Id="Domain" Title="Domain" Converter="String"/>
      <JsonPath Expr="result.visible" Id="Visible" Title="Visible" Converter="Double"/>
      <JsonPath Expr="result.old_visible" Id="OldVisible" Title="Old Visible" Converter="Double"/>
      <JsonPath Expr="result.keywords" Id="Keywords" Title="Keywords" Converter="Int"/>
      <JsonPath Expr="result.traff" Id="Traffic" Title="Traffic" Converter="String"/>
      <JsonPath Expr="result.visible_dynamic" Id="VisibleDynamic" Title="Visible Dynamic" Converter="Double"/>
      <JsonPath Expr="result.traff_dynamic" Id="TrafficDynamic" Title="Traffic Dynamic" Converter="Int"/>
      <JsonPath Expr="result.ads_dynamic" Id="AdsDynamic" Title="Ads Dynamic" Converter="Int"/>
      <JsonPath Expr="result.date" Id="Date" Title="Date" Converter="DateTime"/>
      <JsonPath Expr="result.new_keywords" Id="NewKeywords" Title="New Keywords" Converter="Int"/>
      <JsonPath Expr="result.rised_keywords" Id="RisedKeywords" Title="Rised Keywords" Converter="Int"/>
      <JsonPath Expr="result.down_keywords" Id="DownKeywords" Title="Down Keywords" Converter="Int"/>
      <JsonPath Expr="result.ad_keywords" Id="AdKeywords" Title="Ad Keywords" Converter="Int"/>
      <JsonPath Expr="result.ads" Id="Ads" Title="Ads" Converter="Int"/>
      <JsonPath Expr="result.prev_date" Id="PreviousDate" Title="PreviousDate" Converter="DateTime"/>
    </Parse>
  </RestConnector>

  <RestConnector Id="DomainHistory" Title="Domain History" Group="Domain Reports" HelpText="This report provides you with the historical data on a domain’s number of keywords and visibility." HelpUrl="https://serpstat.com/api/16-domain-summary-report-domainhistory/">
    <Parameters>
      <Text Id="Domain" Title="Domain" Debug.DefaultValue="apple.com" Required="true"/>
      <Resource Id="SelectEngine"/>
    </Parameters>
    <Paging PageSize="100"/>
    <Fetch>
      <Fetch.Url>
        <![CDATA[
        http://api.serpstat.com/v3/domain_history?token=@Model.Key
        &query=@Utils.UrlEncode(Model.Domain)
        &se=@Model.Engine
        &page_size=@(Model.PageCursor.NextTake)
        &page=@(Model.PageCursor.Page)
        ]]>
      </Fetch.Url>
    </Fetch>
    <Parse>
      <JsonPath Expr="result.*">
        <JsonPath Expr="date" Id="Date" Title="Date" Converter="DateTime"/>
        <JsonPath Expr="visible" Id="Visible" Title="Visible" Converter="Double"/>
        <JsonPath Expr="traff" Id="Traffic" Title="Traffic" Converter="String"/>
        <JsonPath Expr="keywords" Id="Keywords" Title="Keywords" Converter="Int"/>
        <JsonPath Expr="ads" Id="Ads" Title="Ads" Converter="Int"/>
        <JsonPath Expr="cost_min" Id="MinimumCost" Title="Minimum Cost" Converter="Double"/>
        <JsonPath Expr="cost_max" Id="MaximumCost" Title="Maximum Cost" Converter="Double"/>
        <JsonPath Expr="new_keywords" Id="NewKeywords" Title="New Keywords" Converter="Int"/>
        <JsonPath Expr="rised_keywords" Id="RisedKeywords" Title="Rised Keywords" Converter="Int"/>
        <JsonPath Expr="down_keywords" Id="DownKeywords" Title="Down Keywords" Converter="Int"/>
        <JsonPath Expr="ad_keywords" Id="AdKeywords" Title="Ad Keywords" Converter="Int"/>
        <JsonPath Expr="out_keywords" Id="Outkeywords" Title="Out Keywords" Converter="Int"/>
      </JsonPath>
    </Parse>
  </RestConnector>

  <RestConnector Id="DomainKeywords" Title="Domain Organic Keywords" Group="Domain Reports" HelpText="This report shows keywords a domain ranks for in Google top 100 search results." HelpUrl="https://serpstat.com/api/18-domain-organic-keywords-domainkeywords/">
    <Parameters>
      <Text Id="Domain" Title="Domain" Debug.DefaultValue="imdb.com" Required="true"/>
      <Text Id="Url" Title="Filter by URL" Debug.DefaultValue="http://www.imdb.com/chart/top"/>
      <Text Id="IncludeKeywords" Title="Filter by Keywords (comma-separated)" Debug.DefaultValue="best"/>
      <Text Id="ExcludeKeywords" Title="Exclude Keywords (comma-separated)" Debug.DefaultValue="movies"/>
      <Number Id="QueriesMinimum" Title="Minimum Queries Count"/>
      <Number Id="QueriesMaximum" Title="Maximum Queries Count"/>
      <Resource Id="SelectEngine"/>
    </Parameters>
    <Paging PageSize="100"/>
    <Fetch>
      <Fetch.Url>
        <![CDATA[
        http://api.serpstat.com/v3/domain_keywords?token=@Model.Key
        &query=@Utils.UrlEncode(Model.Domain)
        @if(!string.IsNullOrEmpty(Model.Url))
        {
          @: &url=@Utils.UrlEncode(Model.Url)
        }
        @if(!string.IsNullOrEmpty(Model.IncludeKeywords))
        {
          @: &keywords=@Utils.UrlEncode(Model.IncludeKeywords)
        }
        @if(!string.IsNullOrEmpty(Model.ExcludeKeywords))
        {
          @: &minus_keywords=@Utils.UrlEncode(Model.ExcludeKeywords)
        }
        @if(Model.QueriesMinimum != 0)
        {
          @: &queries_from=@Utils.UrlEncode(Model.QueriesMinimum)
        }
        @if(Model.QueriesMaximum != 0)
        {
          @: &queries_to=@Utils.UrlEncode(Model.QueriesMaximum)
        }
        &se=@Model.Engine
        &page_size=@(Model.PageCursor.NextTake)
        &page=@(Model.PageCursor.Page)
        ]]>
      </Fetch.Url>
    </Fetch>
    <Parse>
      <JsonPath Expr="result.hits.*">
        <JsonPath Expr="keyword" Id="Keyword" Title="Keyword" Converter="String"/>
        <JsonPath Expr="found_results" Id="FoundResults" Title="Results Found" Converter="String"/>
        <JsonPath Expr="region_queries_count" Id="QueriesCount" Title="Queries Count" Converter="Int"/>
        <JsonPath Expr="dynamic" Id="Dynamic" Title="Dynamic" Converter="Int"/>
        <JsonPath Expr="keyword_crc" Id="KeywordCrc" Title="Keyword CRC" Converter="String"/>
        <JsonPath Expr="url_crc" Id="UrlCrc" Title="URL CRC" Converter="String"/>
        <JsonPath Expr="cost" Id="Cost" Title="Cost" Converter="Double"/>
        <JsonPath Expr="date" Id="Date" Title="Date" Converter="DateTime"/>
        <JsonPath Expr="keyword_id" Id="keywordId" Title="Keyword Id" Converter="Int"/>
        <JsonPath Expr="subdomain" Id="SubDomain" Title="Subdomain" Converter="String"/>
      </JsonPath>
    </Parse>
  </RestConnector>

  <RestConnector Id="DomainsCommonKeywords" Title="Domains Common Keywords" Group="Domain Reports" HelpText="Shows common keywords of up to 3 domains." HelpUrl="https://serpstat.com/api/22-domain-comparison-common-and-unique-keywords-domainsintersection-domainsuniqkeywords/">
    <Parameters>
      <Text Id="Domain" Title="Domain" Debug.DefaultValue="nintendo.com" Required="true"/>
      <Text Id="Domain2" Title="Second Domain" Debug.DefaultValue="microsoft.com" Required="true"/>
      <Text Id="Domain3" Title="Third Domain (optional)" Debug.DefaultValue="youtube.com"/>
      <Resource Id="SelectEngine"/>
    </Parameters>
    <Paging PageSize="100"/>
    <Fetch>
      <Fetch.Url>
        <![CDATA[
        http://api.serpstat.com/v3/domains_intersection?token=@Model.Key
        &query=@Utils.UrlEncode(Model.Domain)
        ,@Utils.UrlEncode(Model.Domain2)
        @if(!string.IsNullOrEmpty(Model.Domain3))
        {
          @: ,@Utils.UrlEncode(Model.Domain3)
        }
        &se=@Model.Engine
        &page_size=@(Model.PageCursor.NextTake)
        &page=@(Model.PageCursor.Page)
        ]]>
      </Fetch.Url>
    </Fetch>
    <Parse>
      <JsonPath Expr="result.hits.*">
        <JsonPath Expr="keyword" Id="Keyword" Title="Keyword" Converter="String"/>
        <JsonPath Expr="found_results" Id="FoundResults" Title="Results Found" Converter="String"/>
        <JsonPath Expr="region_queries_count" Id="RegionQueriesCount" Title="Queries Count" Converter="Int"/>
        <JsonPath Expr="keyword_crc" Id="KeywordCrc" Title="Keyword CRC" Converter="String"/>
        <JsonPath Expr="url_crc" Id="UrlCrc" Title="URL CRC" Converter="String"/>
        <JsonPath Expr="concurrency" Id="Concurrency" Title="Concurrency" Converter="Int"/>
        <JsonPath Expr="cost" Id="Cost" Title="Cost" Converter="Double"/>
        <JsonPath Expr="date" Id="Date" Title="Date" Converter="DateTime"/>
        <JsonPath Expr="keyword_id" Id="keywordId" Title="Keyword Id" Converter="Int"/>
        <JsonPath Expr="url1" Id="Url1" Title="URL 1" Converter="String"/>
        <JsonPath Expr="position1" Id="Position1" Title="Position 1" Converter="String"/>
        <JsonPath Expr="dynamic1" Id="Dynamic1" Title="Dynamic 1" Converter="String"/>
        <JsonPath Expr="url2" Id="Url2" Title="URL 2" Converter="String"/>
        <JsonPath Expr="position2" Id="Position2" Title="Position 2" Converter="String"/>
        <JsonPath Expr="dynamic2" Id="Dynamic2" Title="Dynamic 2" Converter="String"/>
        <JsonPath Expr="url3" Id="Url2" Title="URL 3" Converter="String" Checked="false"/>
        <JsonPath Expr="position3" Id="Position3" Title="Position 3" Converter="String" Checked="false"/>
        <JsonPath Expr="dynamic3" Id="Dynamic3" Title="Dynamic 3" Converter="String" Checked="false"/>
      </JsonPath>
    </Parse>
  </RestConnector>

  <RestConnector Id="DomainUniqueKeywords" Title="Domain Unique Keywords" Group="Domain Reports" HelpText="Shows unique keywords of a domain. Keywords that queried domain has in common with one or two other domains are removed from the list. " HelpUrl="https://serpstat.com/api/65-domain-comparison-common-and-unique-keywords-domainsuniqkeywords/">
    <Parameters>
      <Text Id="Domain" Title="Domain" Debug.DefaultValue="nintendo.com" Required="true"/>
      <Text Id="DomainExclude" Title="Exclude Common KW:s With Domain" Debug.DefaultValue="youtube.com" Required="true" HelpText="domain which keywords should be removed from the results."/>
      <Resource Id="SelectEngine"/>
    </Parameters>
    <Paging PageSize="100"/>
    <Fetch>
      <Fetch.Url>
        <![CDATA[
        http://api.serpstat.com/v3/domains_uniq_keywords?token=@Model.Key
        &query=@Utils.UrlEncode(Model.Domain)
        &minus_domain=@Utils.UrlEncode(Model.DomainExclude)
        &se=@Model.Engine
        &page_size=@(Model.PageCursor.NextTake)
        &page=@(Model.PageCursor.Page)
        ]]>
      </Fetch.Url>
    </Fetch>
    <Parse>
      <JsonPath Expr="result.hits.*">
        <JsonPath Expr="keyword" Id="Keyword" Title="Keyword" Converter="String"/>
        <JsonPath Expr="found_results" Id="FoundResults" Title="Results Found" Converter="String"/>
        <JsonPath Expr="region_queries_count" Id="RegionQueriesCount" Title="Queries Count" Converter="Int"/>
        <JsonPath Expr="keyword_crc" Id="KeywordCrc" Title="Keyword CRC" Converter="String"/>
        <JsonPath Expr="url_crc" Id="UrlCrc" Title="URL CRC" Converter="String"/>
        <JsonPath Expr="concurrency" Id="Concurrency" Title="Concurrency" Converter="Int"/>
        <JsonPath Expr="cost" Id="Cost" Title="Cost" Converter="Double"/>
        <JsonPath Expr="date" Id="Date" Title="Date" Converter="DateTime"/>
        <JsonPath Expr="keyword_id" Id="keywordId" Title="Keyword Id" Converter="Int"/>
        <JsonPath Expr="subdomain" Id="SubDomain" Title="Subdomain" Converter="String"/>
      </JsonPath>
    </Parse>
  </RestConnector>

  <RestConnector Id="UrlsWithinDomain" Title="URLs Within Domain" Group="Domain Reports" HelpText="Returns the list of URLs within the analyzed domain. Also, shows the number of keywords from top-100 for each URL." HelpUrl="https://serpstat.com/api/20-list-of-domains-urls-domainurls/">
    <Parameters>
      <Text Id="Domain" Title="Domain" Debug.DefaultValue="nintendo.com" Required="true"/>
      <Resource Id="SelectEngine"/>
    </Parameters>
    <Paging PageSize="100"/>
    <Fetch>
      <Fetch.Url>
        <![CDATA[
        http://api.serpstat.com/v3/domain_urls?token=@Model.Key
        &query=@Utils.UrlEncode(Model.Domain)
        &se=@Model.Engine
        &page_size=@(Model.PageCursor.NextTake)
        &page=@(Model.PageCursor.Page)
        ]]>
      </Fetch.Url>
    </Fetch>
    <Parse>
      <JsonPath Expr="result.hits.*">
        <JsonPath Expr="url" Id="Url" Title="URL" Converter="String"/>
        <JsonPath Expr="keywords" Id="Keywords" Title="Keywords" Converter="Int"/>
      </JsonPath>
    </Parse>
  </RestConnector>

  <RestConnector Id="DomainCompetitors" Title="Domain Competitors" Group="Domain Reports" HelpText="This report lists domain’s competitors in top 20 Google search results." HelpUrl="https://serpstat.com/api/23-domain-competitors-in-organic-search-competitors/">
    <Parameters>
      <Text Id="Domain" Title="Domain" Debug.DefaultValue="nintendo.com" Required="true"/>
      <Resource Id="SelectEngine"/>
    </Parameters>
    <Fetch>
      <Fetch.Url>
        <![CDATA[
        http://api.serpstat.com/v3/competitors?token=@Model.Key
        &query=@Utils.UrlEncode(Model.Domain)
        &se=@Model.Engine
        ]]>
      </Fetch.Url>
    </Fetch>
    <Parse>
      <JsonPath Expr="result.*">
        <JsonPath Expr="domain" Id="Domain" Title="Competitor Domain" Converter="String"/>
        <JsonPath Expr="visible" Id="Visible" Title="Visible" Converter="Double"/>
        <JsonPath Expr="old_visible" Id="OldVisible" Title="Old Visible" Converter="Double"/>
        <JsonPath Expr="keywords" Id="Keywords" Title="Keywords" Converter="Int"/>
        <JsonPath Expr="traff" Id="Traffic" Title="Traffic" Converter="String"/>
        <JsonPath Expr="ads_dynamic" Id="AdsDynamic" Title="Ads Dynamic" Converter="Int"/>
        <JsonPath Expr="date" Id="Date" Title="Date" Converter="DateTime"/>
        <JsonPath Expr="new_keywords" Id="NewKeywords" Title="New Keywords" Converter="Int"/>
        <JsonPath Expr="rised_keywords" Id="RisedKeywords" Title="Rised Keywords" Converter="Int"/>
        <JsonPath Expr="down_keywords" Id="DownKeywords" Title="Down Keywords" Converter="Int"/>
        <JsonPath Expr="ad_keywords" Id="AdKeywords" Title="Ad Keywords" Converter="Int"/>
        <JsonPath Expr="ads" Id="Ads" Title="Ads" Converter="Int"/>
        <JsonPath Expr="prev_date" Id="PreviousDate" Title="PreviousDate" Converter="DateTime"/>
      </JsonPath>
    </Parse>
  </RestConnector>

  <RestConnector Id="KeywordsFromPhrase" Title="Keywords From Phrase" Group="Keyword Reports" HelpText="This method uses a full-text search to find all keywords that match the queried term." HelpUrl="https://serpstat.com/api/29-phrase-match-keywords-keywords/">
    <Parameters>
      <Text Id="Phrase" Title="Phrase (At least one space is requred" Debug.DefaultValue="seo tools" Required="true" HelpText="This method uses a full text search to find all keywords that match the queried term."/>
      <Number Id="QueriesMinimum" Title="Minimum Queries Count"/>
      <Number Id="QueriesMaximum" Title="Maximum Queries Count"/>
      <Resource Id="SelectEngine"/>
    </Parameters>
    <Paging PageSize="100"/>
    <Fetch>
      <Fetch.Url>
        <![CDATA[
        http://api.serpstat.com/v3/keywords?token=@Model.Key
        &query=@Utils.UrlEncode(Model.Phrase)
        &se=@Model.Engine
        &page_size=@(Model.PageCursor.NextTake)
        &page=@(Model.PageCursor.Page)
        @if(Model.QueriesMinimum != 0)
        {
          @: &queries_from=@Utils.UrlEncode(Model.QueriesMinimum)
        }
        @if(Model.QueriesMaximum != 0)
        {
          @: &queries_to=@Utils.UrlEncode(Model.QueriesMaximum)
        }
        ]]>
      </Fetch.Url>
    </Fetch>
    <Parse>
      <JsonPath Expr="result.hits.*">
        <JsonPath Expr="keyword" Id="Keyword" Title="Keyword" Converter="String"/>
        <JsonPath Expr="cost" Id="Cost" Title="Cost" Converter="Double"/>
        <JsonPath Expr="found_results" Id="FoundResults" Title="Found Results" Converter="String"/>
        <JsonPath Expr="region_queries_count" Id="RegionQueriesCount" Title="Queries Count" Converter="String"/>
        <JsonPath Expr="region_queries_count_last" Id="RegionQueriesLastCount" Title="Queries Last Count" Converter="String"/>
        <JsonPath Expr="keyword_id" Id="KeywordId" Title="Keyword Id" Converter="Int"/>
      </JsonPath>
    </Parse>
  </RestConnector>

  <RestConnector Id="KeywordSummary" Title="Keyword Summary" Group="Keyword Reports" HelpText="This report provides you with the keyword overview showing its volume, CPC and level of competition." HelpUrl="https://serpstat.com/api/31-keyword-overview-keywordinfo/">
    <Parameters>
      <Text Id="Keyword" Title="Keyword" Debug.DefaultValue="seo tools" Required="true"/>
      <Resource Id="SelectEngine"/>
    </Parameters>
    <Fetch>
      <Fetch.Url>
        <![CDATA[
        http://api.serpstat.com/v3/keyword_info?token=@Model.Key
        &query=@Utils.UrlEncode(Model.Keyword)
        &se=@Model.Engine
        ]]>
      </Fetch.Url>
    </Fetch>
    <Parse>
      <JsonPath Expr="result.">
        <JsonPath Expr="keyword" Id="Keyword" Title="Keyword" Converter="String"/>
        <JsonPath Expr="concurrency" Id="Concurrency" Title="Concurrency" Converter="Int"/>
        <JsonPath Expr="cost" Id="Cost" Title="Cost" Converter="Double"/>
        <JsonPath Expr="suggestions_count" Id="SuggestionsCount" Title="Suggestions Count" Converter="Int"/>
        <JsonPath Expr="keywords_count" Id="KeywordsCount" Title="Keywords Count" Converter="Int"/>
        <JsonPath Expr="types" Id="Types" Title="Types" Converter="String"/>
        <JsonPath Expr="social_domains" Id="SocialDomains" Title="Social Domains" Converter="String"/>
        <JsonPath Expr="found_results" Id="FoundResults" Title="Found Results" Converter="String"/>
        <JsonPath Expr="region_queries_count" Id="RegionQueriesCount" Title="Queries Count" Converter="Int"/>
        <JsonPath Expr="region_queries_count_last" Id="RegionQueriesCountLast" Title="Queries Count Last" Converter="Int"/>
        <JsonPath Expr="id" Id="KeywordId" Title="Keyword Id" Converter="Int"/>
      </JsonPath>
    </Parse>
  </RestConnector>

  <RestConnector Id="KeywordAutocompletes" Title="Keyword Search Suggestions" Group="Keyword Reports" HelpText="These report lists autocomplete suggestions for the keyword you requested (they are found by the full-text search)." HelpUrl="https://serpstat.com/api/33-keyword-search-suggestions-suggestions/">
    <Parameters>
      <Text Id="Keyword" Title="Keyword" Debug.DefaultValue="seo tools" Required="true"/>
      <Resource Id="SelectEngine"/>
    </Parameters>
    <Fetch>
      <Fetch.Url>
        <![CDATA[
        http://api.serpstat.com/v3/suggestions?token=@Model.Key
        &query=@Utils.UrlEncode(Model.Keyword)
        &se=@Model.Engine
        ]]>
      </Fetch.Url>
    </Fetch>
    <Parse>
      <JsonPath Expr="result.hits.*">
        <JsonPath Expr="keyword" Id="Keyword" Title="Keyword" Converter="String"/>
      </JsonPath>
    </Parse>
  </RestConnector>

  <RestConnector Id="KeywordsRelated" Title="Keywords Related" Group="Keyword Reports" HelpText="This report gives you a comprehensive list of related keywords whose SERP is similar to the one the requested keyword has." HelpUrl="https://serpstat.com/api/35-related-keywords-relatedkeywords/">
    <Parameters>
      <Text Id="Keyword" Title="Keyword" Debug.DefaultValue="seo tools" Required="true"/>
      <Number Id="ConnectionStrength" Title="Minimum Connection Strength (1-20)" HelpText="Criteria for the degree of keywords similarity. Serpstat finds related keywords according to the similarity of their top-20 search results."/>
      <Resource Id="SelectEngine"/>
    </Parameters>
    <Paging PageSize="100"/>
    <Fetch>
      <Fetch.Url>
        <![CDATA[
        http://api.serpstat.com/v3/related_keywords?token=@Model.Key
        &query=@Utils.UrlEncode(Model.Keyword)
        @if(Model.ConnectionStrength != 0)
        {
          @: &weight=@Utils.UrlEncode(Model.ConnectionStrength)
        }
        &se=@Model.Engine
        &page_size=@(Model.PageCursor.NextTake)
        &page=@(Model.PageCursor.Page)
        ]]>
      </Fetch.Url>
    </Fetch>
    <Parse>
      <JsonPath Expr="result.hits.*">
        <JsonPath Expr="keyword" Id="Keyword" Title="Keyword" Converter="String"/>
        <JsonPath Expr="concurrency" Id="Concurrency" Title="Concurrency" Converter="Int"/>
        <JsonPath Expr="cost" Id="Cost" Title="Cost" Converter="Double"/>
        <JsonPath Expr="types" Id="Types" Title="Types" Converter="String"/>
        <JsonPath Expr="weight" Id="ConnectionStrength" Title="Connection Strength" Converter="Int"/>
      </JsonPath>
    </Parse>
  </RestConnector>

  <RestConnector Id="KeywordTopSearchResults" Title="Keyword Top Search Results" Group="Keyword Reports" HelpText="This report shows you Google top 100 organic search results for the keyword you requested." HelpUrl="https://serpstat.com/api/37-top-for-a-keyword-keywordtop/">
    <Parameters>
      <Text Id="Keyword" Title="Keyword" Debug.DefaultValue="seo tools" Required="true"/>
      <Resource Id="SelectEngine"/>
    </Parameters>
    <Fetch>
      <Fetch.Url>
        <![CDATA[
        http://api.serpstat.com/v3/keyword_top?token=@Model.Key
        &query=@Utils.UrlEncode(Model.Keyword)
        &se=@Model.Engine
        ]]>
      </Fetch.Url>
    </Fetch>
    <Parse>
      <JsonPath Expr="result.top.*">
        <JsonPath Expr="url" Id="Url" Title="URL" Converter="String"/>
        <JsonPath Expr="domain" Id="Domain" Title="Domain" Converter="String"/>
        <JsonPath Expr="snippet" Id="Snippet" Title="Snippet" Converter="String"/>
        <JsonPath Expr="title" Id="Title" Title="Title" Converter="String"/>
      </JsonPath>
    </Parse>
  </RestConnector>

  <RestConnector Id="KeywordAdvertisingReport" Title="Keyword Advertising Report" Group="Keyword Reports" HelpText="This report shows you ads copies that pop up for the queried keyword in Google paid search results." HelpUrl="https://serpstat.com/api/41-advertising-report-adkeywords/">
    <Parameters>
      <Text Id="Keyword" Title="Keyword" Debug.DefaultValue="seo tools" Required="true"/>
      <Number Id="QueriesMinimum" Title="Minimum Queries Count"/>
      <Number Id="QueriesMaximum" Title="Maximum Queries Count"/>
      <Resource Id="SelectEngine"/>
    </Parameters>
    <Paging PageSize="100"/>
    <Fetch>
      <Fetch.Url>
        <![CDATA[
        http://api.serpstat.com/v3/ad_keywords?token=@Model.Key
        &query=@Utils.UrlEncode(Model.Keyword)
        &se=@Model.Engine
        &page_size=@(Model.PageCursor.NextTake)
        &page=@(Model.PageCursor.Page)
        @if(Model.QueriesMinimum != 0)
        {
          @: &queries_from=@Utils.UrlEncode(Model.QueriesMinimum)
        }
        @if(Model.QueriesMaximum != 0)
        {
          @: &queries_to=@Utils.UrlEncode(Model.QueriesMaximum)
        }
        ]]>
      </Fetch.Url>
    </Fetch>
    <Parse>
      <JsonPath Expr="result.hits.*">
        <JsonPath Expr="url" Id="Url" Title="URL" Converter="String"/>
        <JsonPath Expr="domain" Id="Domain" Title="Domain" Converter="String"/>
        <JsonPath Expr="text" Id="Text" Title="Text" Converter="String"/>
        <JsonPath Expr="title" Id="Title" Title="Title" Converter="String"/>
        <JsonPath Expr="cost" Id="Cost" Title="Cost" Converter="Double"/>
        <JsonPath Expr="url_crc" Id="UrlCrc" Title="URL CRC" Converter="String"/>
        <JsonPath Expr="crc" Id="Crc" Title="CRC" Converter="String"/>
        <JsonPath Expr="found_results" Id="FoundResults" Title="Found Results" Converter="String"/>
        <JsonPath Expr="region_queries_count" Id="RegionQueriesCount" Title="Queries Count" Converter="Int"/>
      </JsonPath>
    </Parse>
  </RestConnector>

  <RestConnector Id="UrlKeywords" Title="URL Keywords" Group="URL Reports" HelpText="The report lists keywords that URL ranks for in Google search results." HelpUrl="https://serpstat.com/api/45-url-organic-keywords-urlkeywords/">
    <Parameters>
      <Text Id="Url" Title="URL" Debug.DefaultValue="http://www.imdb.com/chart/top" Required="true"/>
      <Resource Id="SelectEngine"/>
    </Parameters>
    <Paging PageSize="100"/>
    <Fetch>
      <Fetch.Url>
        <![CDATA[
        http://api.serpstat.com/v3/url_keywords?token=@Model.Key
        &query=@Utils.UrlEncode(Model.Url)
        &se=@Model.Engine
        &page_size=@(Model.PageCursor.NextTake)
        &page=@(Model.PageCursor.Page)
        ]]>
      </Fetch.Url>
    </Fetch>
    <Parse>
      <JsonPath Expr="result.hits.*">
        <JsonPath Expr="keyword" Id="Keyword" Title="Keyword" Converter="String"/>
        <JsonPath Expr="concurrency" Id="Concurrency" Title="Concurrency" Converter="Int"/>
        <JsonPath Expr="cost" Id="Cost" Title="Cost" Converter="Double"/>
        <JsonPath Expr="url_crc" Id="UrlCrc" Title="URL CRC" Converter="String"/>
        <JsonPath Expr="keyword_crc" Id="KeywordCrc" Title="Keyword CrRC" Converter="String"/>
        <JsonPath Expr="found_results" Id="FoundResults" Title="Found Results" Converter="String"/>
      </JsonPath>
    </Parse>
  </RestConnector>

  <RestConnector Id="UrlCompetitors" Title="URL Competitors" Group="URL Reports" HelpText="Shows the list of URLs that compete with a queried URL in organic search." HelpUrl="https://serpstat.com/api/47-list-of-urls-that-compete-with-a-queried-page-urlcompetitors/">
    <Parameters>
      <Text Id="Url" Title="URL" Debug.DefaultValue="http://www.imdb.com/chart/top" Required="true"/>
      <Resource Id="SelectEngine"/>
    </Parameters>
    <Paging PageSize="100"/>
    <Fetch>
      <Fetch.Url>
        <![CDATA[
        http://api.serpstat.com/v3/url_competitors?token=@Model.Key
        &query=@Utils.UrlEncode(Model.Url)
        &se=@Model.Engine
        &page_size=@(Model.PageCursor.NextTake)
        &page=@(Model.PageCursor.Page)
        ]]>
      </Fetch.Url>
    </Fetch>
    <Parse>
      <JsonPath Expr="result.hits.*">
        <JsonPath Expr="url" Id="Url" Title="URL" Converter="String"/>
        <JsonPath Expr="domain" Id="Domain" Title="Domain" Converter="String"/>
        <JsonPath Expr="cnt" Id="Count" Title="Count" Converter="Int"/>
      </JsonPath>
    </Parse>
  </RestConnector>

  <RestConnector Id="UrlMissingKeywords" Title="URL Missing Competitors Keywords" Group="URL Reports" HelpText="Shows a list of keywords that competitors' URLs rank for in top-10 but that are missing from the queried page." HelpUrl="https://serpstat.com/api/49-competitors-keywords-that-are-missing-from-a-queried-page-urlmissingkeywords/">
    <Parameters>
      <Text Id="Url" Title="URL" Debug.DefaultValue="http://www.imdb.com/chart/top" Required="true"/>
      <Resource Id="SelectEngine"/>
    </Parameters>
    <Paging PageSize="100"/>
    <Fetch>
      <Fetch.Url>
        <![CDATA[
        http://api.serpstat.com/v3/url_missing_keywords?token=@Model.Key
        &query=@Utils.UrlEncode(Model.Url)
        &se=@Model.Engine
        &page_size=@(Model.PageCursor.NextTake)
        &page=@(Model.PageCursor.Page)
        ]]>
      </Fetch.Url>
    </Fetch>
    <Parse>
      <JsonPath Expr="result.hits.*">
        <JsonPath Expr="keyword" Id="Keyword" Title="Keyword" Converter="String"/>
        <JsonPath Expr="region_queries_count" Id="RegionQueriesCount" Title="Queries Count" Converter="Int"/>
        <JsonPath Expr="weight" Id="ConnectionStrength" Title="Connection Strength" Converter="Int"/>
        <JsonPath Expr="keyword_id" Id="KeywordId" Title="Keyword Id" Converter="Int"/>
      </JsonPath>
    </Parse>
  </RestConnector>

  <RestConnector Id="AvailableRequests" Title="Available API Requests" HelpText="Check the number of requests you can perform within your daily limit" HelpUrl="">
    <Fetch>
      <Fetch.Url>
        <![CDATA[
        http://api.serpstat.com/v3/stats?token=@Model.Key&se=g_us
        ]]>
      </Fetch.Url>
    </Fetch>
    <Parse>
			<JsonPath Expr="result.max_lines" Id="TotalLines" Title="Total Lines" Converter="Int"/>
			<JsonPath Expr="result.used_lines" Id="UsedLines" Title="Used Lines" Converter="Int"/>
			<JsonPath Expr="result.left_lines" Id="LeftLines" Title="Left Lines" Converter="Int"/>
			<JsonPath Expr="result.max_results" Id="MaxResults" Title="Max Results" Converter="Int"/>
    </Parse>
  </RestConnector>

</Suite>